qai/ai/__init__.py
qai/ai/config.py
qai/ai/frameworks/__init__.py
qai/ai/frameworks/llama/__init__.py
qai/ai/frameworks/llama/assistant.py
qai/ai/frameworks/llama/chat.py
qai/ai/frameworks/llama/embeddings.py
qai/ai/frameworks/llama/llama_chroma.py
qai/ai/frameworks/openai/llm.py
qai/ai/llm.py
qai/ai/mock/mock.py
qai/ai/prompt/__init__.py
qai/ai/prompt/config.py
qai/ai/query.py
qai/ai/utils/config_utils.py
qai/ai/utils/nltk_extras.py
qai/ai/utils/nltk_utils.py
qai/ai/utils/openai_utils.py
qai/ai/utils/token_utils.py
qai/ai/utils/validation_utils.py
qai_ai-0.6.1.dist-info/METADATA
qai_ai-0.6.1.dist-info/WHEEL
qai_ai-0.6.1.dist-info/RECORD
