Metadata-Version: 2.1
Name: qai-ai
Version: 0.6.1
Summary: Qai AI API
Author: parnell
Author-email: 152523161+leeparnell@users.noreply.github.com
Requires-Python: >=3.11,<3.12
Classifier: Programming Language :: Python :: 3
Classifier: Programming Language :: Python :: 3.11
Requires-Dist: chromadb (>=0.5.5,<0.6.0)
Requires-Dist: dataclasses-json (>=0.6.4,<0.7.0)
Requires-Dist: huggingface (>=0.0.1,<0.0.2)
Requires-Dist: langchain-community (>=0.0.34,<0.0.35)
Requires-Dist: llama-index (>=0.10.30,<0.11.0)
Requires-Dist: llama-index-embeddings-huggingface (>=0.2.0,<0.3.0)
Requires-Dist: llama-index-llms-huggingface (>=0.2.5,<0.3.0)
Requires-Dist: llama-index-vector-stores-chroma (>=0.1.7,<0.2.0)
Requires-Dist: openai (>=1.23.2,<2.0.0)
Requires-Dist: pandas (>=2.2.1,<3.0.0)
Requires-Dist: pi-conf (>=0.8.5.1,<0.9.0.0)
Requires-Dist: pi-log (>=0.5.8.1,<0.6.0.0)
Requires-Dist: qai-storage (>=0.6.1,<0.7.0)
Requires-Dist: termcolor (>=2.4.0,<3.0.0)
